config_state/__init__.py
config_state/buildable.py
config_state/config_state.py
config_state/exceptions.py
config_state/misc.py
config_state/serializers/__init__.py
config_state/serializers/_json.py
config_state/serializers/_pickle.py
config_state/serializers/serializer.py
config_state-1.0.2.dist-info/METADATA
config_state-1.0.2.dist-info/WHEEL
config_state-1.0.2.dist-info/licenses/LICENSE
config_state-1.0.2.dist-info/RECORD
