Metadata-Version: 2.1
Name: config-state
Version: 1.0.2
Summary: config-state is a Python module for implementing classes with the `ConfigState` pattern. The pattern augments classes with  configuration and state semantics enabling their instantiation through configuration files together with an improved control over their (de)serialization logics.
Home-page: https://github.com/nicolaspi/config-state
Author: Nicolas Pinchaud
Author-email: nicolas.pinchaud@gmail.com
Classifier: Programming Language :: Python :: 3
Classifier: Operating System :: OS Independent
Requires-Python: >=3.7
License-File: LICENSE
Requires-Dist: pyyaml
